secrets_hunter/__init__.py
secrets_hunter/cli.py
secrets_hunter/scanner.py
secrets_hunter/config/__init__.py
secrets_hunter/config/ignore.toml
secrets_hunter/config/loader.py
secrets_hunter/config/patterns.toml
secrets_hunter/config/settings.py
secrets_hunter/detectors/__init__.py
secrets_hunter/detectors/base.py
secrets_hunter/detectors/entropy_detector.py
secrets_hunter/detectors/pattern_detector.py
secrets_hunter/detectors/utils/__init__.py
secrets_hunter/detectors/utils/entropy.py
secrets_hunter/detectors/utils/strings_extractor.py
secrets_hunter/detectors/utils/validators.py
secrets_hunter/handlers/__init__.py
secrets_hunter/handlers/file_handler.py
secrets_hunter/handlers/output_formater.py
secrets_hunter/handlers/progress.py
secrets_hunter/models/__init__.py
secrets_hunter/models/finding.py
secrets_hunter/reporters/__init__.py
secrets_hunter/reporters/console_reporter.py
secrets_hunter/reporters/json_reporter.py
secrets_hunter/reporters/sarif_reporter.py
secrets_hunter-0.1.0.dist-info/licenses/LICENSE
secrets_hunter-0.1.0.dist-info/METADATA
secrets_hunter-0.1.0.dist-info/WHEEL
secrets_hunter-0.1.0.dist-info/entry_points.txt
secrets_hunter-0.1.0.dist-info/top_level.txt
secrets_hunter-0.1.0.dist-info/RECORD
