Metadata-Version: 2.4
Name: secrets-hunter
Version: 0.1.0
Summary: Detect secrets and sensitive information in your codebase
Author-email: FVLCN-dev <alex@fvlcn.dev>
License: MIT License
Project-URL: Repository, https://github.com/FVLCN/secrets-hunter
Project-URL: Homepage, https://fvlcn.dev
Keywords: security,secrets,scanner,git,ci
Requires-Python: >=3.11
License-File: LICENSE
Provides-Extra: dev
Requires-Dist: pytest>=7; extra == "dev"
Requires-Dist: pytest-cov>=3; extra == "dev"
Requires-Dist: black; extra == "dev"
Requires-Dist: flake8; extra == "dev"
Requires-Dist: mypy; extra == "dev"
Dynamic: license-file
